{
    "class": "Flow ID #202",
    "top_features": [
        {
            "feature_name": "FIN Flag Cnt",
            "importance": -0.005569302903071733,
            "description": "Number of packets with FIN"
        },
        {
            "feature_name": "Tot Bwd Pkts",
            "importance": -0.004116920511304838,
            "description": "Total packets in the backward direction"
        },
        {
            "feature_name": "Bwd Header Len",
            "importance": 0.003654600166003621,
            "description": "Total bytes used for headers in the backward direction"
        },
        {
            "feature_name": "Flow IAT Mean",
            "importance": 0.0036515151105240688,
            "description": "Mean time between two packets sent in the flow"
        },
        {
            "feature_name": "Bwd IAT Max",
            "importance": 0.002405781638418974,
            "description": "Maximum time between two packets sent in the backward direction"
        },
        {
            "feature_name": "Bwd Pkt Len Min",
            "importance": 0.0019959498476573314,
            "description": "Minimum size of packet in backward direction"
        },
        {
            "feature_name": "Flow Duration",
            "importance": 0.001975354900318341,
            "description": "Duration of the flow in Microsecond"
        },
        {
            "feature_name": "Bwd IAT Mean",
            "importance": 0.0019665232440227868,
            "description": "Mean time between two packets sent in the backward direction"
        },
        {
            "feature_name": "Init Bwd Win Byts",
            "importance": 0.0019404404958458298,
            "description": "The total number of bytes sent in initial window in the backward direction"
        },
        {
            "feature_name": "Bwd PSH Flags",
            "importance": 0.0015916723045497,
            "description": "Number of times the PSH flag was set in packets travelling in the backward direction (0 for UDP)"
        }
    ]
}