{
    "id": 323,
    "top_features": [
        {
            "feature_name": "Fwd IAT Std",
            "importance": -0.010824176310821896,
            "description": "Standard deviation time between two packets sent in the forward direction"
        },
        {
            "feature_name": "Fwd Pkts/s",
            "importance": -0.010095063203696006,
            "description": "Number of forward packets per second"
        },
        {
            "feature_name": "Tot Fwd Pkts",
            "importance": -0.009675613964923103,
            "description": "Total packets in the forward direction"
        },
        {
            "feature_name": "Pkt Len Max",
            "importance": -0.009325218385214157,
            "description": "Maximum length of a packet"
        },
        {
            "feature_name": "Fwd Act Data Pkts",
            "importance": -0.009279007594827419,
            "description": "Count of packets with at least 1 byte of TCP data payload in the forward direction"
        },
        {
            "feature_name": "Fwd Header Len",
            "importance": -0.00825114675340855,
            "description": "Total bytes used for headers in the forward direction"
        },
        {
            "feature_name": "Bwd Pkts/s",
            "importance": -0.006918400565761778,
            "description": "Number of backward packets per second"
        },
        {
            "feature_name": "Fwd Pkt Len Mean",
            "importance": -0.005936108597087052,
            "description": "Mean size of packet in forward direction"
        },
        {
            "feature_name": "Flow Duration",
            "importance": -0.005211396931658208,
            "description": "Duration of the flow in Microsecond"
        },
        {
            "feature_name": "Pkt Len Min",
            "importance": 0.004810381658726464,
            "description": "Minimum length of a packet"
        }
    ]
}