{
    "class": "Flow ID #23",
    "top_features": [
        {
            "feature_name": "Bwd Header Len",
            "importance": -0.00348232528659942,
            "description": "Total bytes used for headers in the backward direction"
        },
        {
            "feature_name": "Flow IAT Mean",
            "importance": 0.0032535426087215162,
            "description": "Mean time between two packets sent in the flow"
        },
        {
            "feature_name": "Fwd Pkt Len Min",
            "importance": 0.0022714417625830812,
            "description": "Minimum size of packet in forward direction"
        },
        {
            "feature_name": "RST Flag Cnt",
            "importance": 0.0021836897363722687,
            "description": "Number of packets with RST"
        },
        {
            "feature_name": "Flow Byts/s",
            "importance": 0.002089060228198909,
            "description": "Number of flow bytes per second"
        },
        {
            "feature_name": "Bwd Pkts/s",
            "importance": -0.0020778461978283153,
            "description": "Number of backward packets per second"
        },
        {
            "feature_name": "Flow Duration",
            "importance": 0.0019336103125732194,
            "description": "Duration of the flow in Microsecond"
        },
        {
            "feature_name": "Fwd Pkt Len Max",
            "importance": -0.001907299568686861,
            "description": "Maximum size of packet in forward direction"
        },
        {
            "feature_name": "Pkt Len Max",
            "importance": -0.0018544369007892768,
            "description": "Maximum length of a packet"
        },
        {
            "feature_name": "PSH Flag Cnt",
            "importance": 0.0017282093328404345,
            "description": "Number of packets with PUSH"
        }
    ]
}