{
    "class": "Flow ID #442",
    "top_features": [
        {
            "feature_name": "Bwd IAT Min",
            "importance": 0.007361622069540869,
            "description": "Minimum time between two packets sent in the backward direction"
        },
        {
            "feature_name": "Tot Bwd Pkts",
            "importance": 0.0057036855833417985,
            "description": "Total packets in the backward direction"
        },
        {
            "feature_name": "Subflow Bwd Pkts",
            "importance": 0.003907543471407638,
            "description": "The average number of packets in a sub flow in the backward direction"
        },
        {
            "feature_name": "Fwd Pkts/s",
            "importance": 0.003082426091247834,
            "description": "Number of forward packets per second"
        },
        {
            "feature_name": "ACK Flag Cnt",
            "importance": 0.00241349304769289,
            "description": "Number of packets with ACK"
        },
        {
            "feature_name": "Init Bwd Win Byts",
            "importance": 0.002413051335308981,
            "description": "The total number of bytes sent in initial window in the backward direction"
        },
        {
            "feature_name": "Flow IAT Min",
            "importance": 0.0022581279928502473,
            "description": "Minimum time between two packets sent in the flow"
        },
        {
            "feature_name": "Bwd IAT Tot",
            "importance": 0.0022259358110321517,
            "description": "Total time between two packets sent in the backward direction"
        },
        {
            "feature_name": "Bwd IAT Mean",
            "importance": 0.002096492802603236,
            "description": "Mean time between two packets sent in the backward direction"
        },
        {
            "feature_name": "Bwd Pkt Len Min",
            "importance": 0.002001383620889717,
            "description": "Minimum size of packet in backward direction"
        }
    ]
}