{
    "class": "Flow ID #324",
    "top_features": [
        {
            "feature_name": "Bwd Header Len",
            "importance": 0.0029499945192026996,
            "description": "Total bytes used for headers in the backward direction"
        },
        {
            "feature_name": "Flow IAT Mean",
            "importance": 0.002825719472922055,
            "description": "Mean time between two packets sent in the flow"
        },
        {
            "feature_name": "Flow Duration",
            "importance": 0.002564227979181336,
            "description": "Duration of the flow in Microsecond"
        },
        {
            "feature_name": "Fwd Pkt Len Min",
            "importance": -0.0021584239655219545,
            "description": "Minimum size of packet in forward direction"
        },
        {
            "feature_name": "Bwd PSH Flags",
            "importance": 0.001902478278199594,
            "description": "Number of times the PSH flag was set in packets travelling in the backward direction (0 for UDP)"
        },
        {
            "feature_name": "Tot Bwd Pkts",
            "importance": -0.0018456362103059633,
            "description": "Total packets in the backward direction"
        },
        {
            "feature_name": "Bwd IAT Max",
            "importance": 0.0017574195482901922,
            "description": "Maximum time between two packets sent in the backward direction"
        },
        {
            "feature_name": "Bwd IAT Mean",
            "importance": 0.001698895082957233,
            "description": "Mean time between two packets sent in the backward direction"
        },
        {
            "feature_name": "Pkt Size Avg",
            "importance": 0.0013138677123245963,
            "description": "Average size of packet"
        },
        {
            "feature_name": "PSH Flag Cnt",
            "importance": 0.0010412811141430277,
            "description": "Number of packets with PUSH"
        }
    ]
}