{
    "class": "Flow ID #391",
    "top_features": [
        {
            "feature_name": "Fwd Pkt Len Mean",
            "importance": -0.013712825808308177,
            "description": "Mean size of packet in forward direction"
        },
        {
            "feature_name": "Bwd Pkts/s",
            "importance": -0.01156013852166726,
            "description": "Number of backward packets per second"
        },
        {
            "feature_name": "Fwd Pkt Len Min",
            "importance": 0.010136199931836539,
            "description": "Minimum size of packet in forward direction"
        },
        {
            "feature_name": "Bwd IAT Tot",
            "importance": -0.009909579108899726,
            "description": "Total time between two packets sent in the backward direction"
        },
        {
            "feature_name": "Init Bwd Win Byts",
            "importance": 0.009355173426675882,
            "description": "The total number of bytes sent in initial window in the backward direction"
        },
        {
            "feature_name": "Fwd IAT Std",
            "importance": -0.008814467733923735,
            "description": "Standard deviation time between two packets sent in the forward direction"
        },
        {
            "feature_name": "Bwd IAT Min",
            "importance": 0.0083789500895502,
            "description": "Minimum time between two packets sent in the backward direction"
        },
        {
            "feature_name": "Bwd PSH Flags",
            "importance": 0.00786694312141582,
            "description": "Number of times the PSH flag was set in packets travelling in the backward direction (0 for UDP)"
        },
        {
            "feature_name": "RST Flag Cnt",
            "importance": 0.007730790131327188,
            "description": "Number of packets with RST"
        },
        {
            "feature_name": "Bwd Pkt Len Min",
            "importance": 0.007136448026043152,
            "description": "Minimum size of packet in backward direction"
        }
    ]
}