{
    "id": 16,
    "top_features": [
        {
            "feature_name": "Bwd Pkts/s",
            "importance": 0.02796900076428881,
            "description": "Number of backward packets per second"
        },
        {
            "feature_name": "PSH Flag Cnt",
            "importance": -0.020369509584377266,
            "description": "Number of packets with PUSH"
        },
        {
            "feature_name": "Fwd IAT Std",
            "importance": -0.011800859529640212,
            "description": "Standard deviation time between two packets sent in the forward direction"
        },
        {
            "feature_name": "FIN Flag Cnt",
            "importance": 0.011175457336071792,
            "description": "Number of packets with FIN"
        },
        {
            "feature_name": "Fwd Pkt Len Mean",
            "importance": -0.010745191638311313,
            "description": "Mean size of packet in forward direction"
        },
        {
            "feature_name": "Init Bwd Win Byts",
            "importance": 0.010272322789281205,
            "description": "The total number of bytes sent in initial window in the backward direction"
        },
        {
            "feature_name": "Pkt Len Min",
            "importance": 0.00779214154592455,
            "description": "Minimum length of a packet"
        },
        {
            "feature_name": "Pkt Len Max",
            "importance": -0.007671110546757764,
            "description": "Maximum length of a packet"
        },
        {
            "feature_name": "Flow IAT Max",
            "importance": -0.006615844655688642,
            "description": "Maximum time between two packets sent in the flow"
        },
        {
            "feature_name": "Bwd Pkt Len Std",
            "importance": -0.005955949524442652,
            "description": "Standard deviation size of packet in backward direction"
        }
    ]
}