{
    "class": "Flow ID #250",
    "top_features": [
        {
            "feature_name": "Idle Std",
            "importance": -0.004538915682846406,
            "description": "Standard deviation time a flow was idle before becoming active"
        },
        {
            "feature_name": "Flow IAT Mean",
            "importance": 0.0037162528342208298,
            "description": "Mean time between two packets sent in the flow"
        },
        {
            "feature_name": "Bwd Header Len",
            "importance": -0.0034688553350537814,
            "description": "Total bytes used for headers in the backward direction"
        },
        {
            "feature_name": "Fwd Pkt Len Min",
            "importance": 0.0030067183303994116,
            "description": "Minimum size of packet in forward direction"
        },
        {
            "feature_name": "Bwd PSH Flags",
            "importance": 0.002895786801578806,
            "description": "Number of times the PSH flag was set in packets travelling in the backward direction (0 for UDP)"
        },
        {
            "feature_name": "RST Flag Cnt",
            "importance": 0.0024355125423817614,
            "description": "Number of packets with RST"
        },
        {
            "feature_name": "Fwd IAT Std",
            "importance": -0.0018905871187232413,
            "description": "Standard deviation time between two packets sent in the forward direction"
        },
        {
            "feature_name": "Bwd Pkts/s",
            "importance": -0.0018808680169921839,
            "description": "Number of backward packets per second"
        },
        {
            "feature_name": "FIN Flag Cnt",
            "importance": 0.0018611860522201073,
            "description": "Number of packets with FIN"
        },
        {
            "feature_name": "Pkt Len Var",
            "importance": 0.0017012654482966322,
            "description": "Variance length of a packet"
        }
    ]
}