{
    "class": "Flow ID #431",
    "top_features": [
        {
            "feature_name": "Bwd Pkts/s",
            "importance": 0.023268243380731714,
            "description": "Number of backward packets per second"
        },
        {
            "feature_name": "Fwd IAT Std",
            "importance": -0.011337955708536096,
            "description": "Standard deviation time between two packets sent in the forward direction"
        },
        {
            "feature_name": "Fwd Pkt Len Mean",
            "importance": -0.009248591859477852,
            "description": "Mean size of packet in forward direction"
        },
        {
            "feature_name": "FIN Flag Cnt",
            "importance": 0.008572247371079044,
            "description": "Number of packets with FIN"
        },
        {
            "feature_name": "Fwd Act Data Pkts",
            "importance": -0.00839423617253467,
            "description": "Count of packets with at least 1 byte of TCP data payload in the forward direction"
        },
        {
            "feature_name": "Init Bwd Win Byts",
            "importance": 0.008390700844268538,
            "description": "The total number of bytes sent in initial window in the backward direction"
        },
        {
            "feature_name": "Pkt Len Max",
            "importance": -0.007579451833997572,
            "description": "Maximum length of a packet"
        },
        {
            "feature_name": "Pkt Len Min",
            "importance": 0.0073833571934956935,
            "description": "Minimum length of a packet"
        },
        {
            "feature_name": "Fwd Pkts/s",
            "importance": 0.006235499356355612,
            "description": "Number of forward packets per second"
        },
        {
            "feature_name": "PSH Flag Cnt",
            "importance": 0.006123179960215609,
            "description": "Number of packets with PUSH"
        }
    ]
}