{
    "class": "Flow ID #53",
    "top_features": [
        {
            "feature_name": "Bwd Pkts/s",
            "importance": 0.01585803615812176,
            "description": "Number of backward packets per second"
        },
        {
            "feature_name": "Pkt Len Min",
            "importance": -0.014176776359462776,
            "description": "Minimum length of a packet"
        },
        {
            "feature_name": "Bwd Pkt Len Min",
            "importance": -0.012649815604462935,
            "description": "Minimum size of packet in backward direction"
        },
        {
            "feature_name": "Pkt Len Max",
            "importance": 0.012426275242771729,
            "description": "Maximum length of a packet"
        },
        {
            "feature_name": "Fwd IAT Std",
            "importance": 0.011040852076423822,
            "description": "Standard deviation time between two packets sent in the forward direction"
        },
        {
            "feature_name": "RST Flag Cnt",
            "importance": 0.010309639875850379,
            "description": "Number of packets with RST"
        },
        {
            "feature_name": "Idle Std",
            "importance": 0.009940372868337675,
            "description": "Standard deviation time a flow was idle before becoming active"
        },
        {
            "feature_name": "Bwd Pkt Len Std",
            "importance": 0.009641931168415151,
            "description": "Standard deviation size of packet in backward direction"
        },
        {
            "feature_name": "Bwd PSH Flags",
            "importance": -0.009500523525120588,
            "description": "Number of times the PSH flag was set in packets travelling in the backward direction (0 for UDP)"
        },
        {
            "feature_name": "Fwd Act Data Pkts",
            "importance": 0.008874723559375465,
            "description": "Count of packets with at least 1 byte of TCP data payload in the forward direction"
        }
    ]
}