{
    "id": 259,
    "top_features": [
        {
            "feature_name": "Bwd Pkts/s",
            "importance": 0.025821704665698136,
            "description": "Number of backward packets per second"
        },
        {
            "feature_name": "Fwd IAT Std",
            "importance": -0.013986737050499846,
            "description": "Standard deviation time between two packets sent in the forward direction"
        },
        {
            "feature_name": "FIN Flag Cnt",
            "importance": 0.011766089622639343,
            "description": "Number of packets with FIN"
        },
        {
            "feature_name": "Flow IAT Min",
            "importance": -0.008943322048200033,
            "description": "Minimum time between two packets sent in the flow"
        },
        {
            "feature_name": "Bwd Pkt Len Min",
            "importance": 0.008718396941862645,
            "description": "Minimum size of packet in backward direction"
        },
        {
            "feature_name": "Bwd PSH Flags",
            "importance": 0.008631503526310098,
            "description": "Number of times the PSH flag was set in packets travelling in the backward direction (0 for UDP)"
        },
        {
            "feature_name": "Init Bwd Win Byts",
            "importance": 0.007986532622917753,
            "description": "The total number of bytes sent in initial window in the backward direction"
        },
        {
            "feature_name": "Pkt Len Max",
            "importance": -0.007753859124112669,
            "description": "Maximum length of a packet"
        },
        {
            "feature_name": "Fwd Pkt Len Mean",
            "importance": -0.007751653730304639,
            "description": "Mean size of packet in forward direction"
        },
        {
            "feature_name": "Bwd Pkt Len Std",
            "importance": -0.007348358446215862,
            "description": "Standard deviation size of packet in backward direction"
        }
    ]
}